dfisher_2022a/.coveragerc
dfisher_2022a/__init__.py
dfisher_2022a/app.py
dfisher_2022a/cube.py
dfisher_2022a/emission_lines.py
dfisher_2022a/exceptions.py
dfisher_2022a/fits/__init__.py
dfisher_2022a/fits/base.py
dfisher_2022a/fits/cpufitter.py
dfisher_2022a/line.py
dfisher_2022a/models/__init__.py
dfisher_2022a/models/base.py
dfisher_2022a/models/lmfit/__init__.py
dfisher_2022a/models/lmfit/base.py
dfisher_2022a/models/lmfit/composite.py
dfisher_2022a/tests/fixtures/eso338_test_run_6563_simple_model.txt
dfisher_2022a/tests/fixtures/single_gaussian_muse_size.fits
dfisher_2022a/tests/test_cube.py
dfisher_2022a/tests/test_fits.py
dfisher_2022a/tests/test_line.py
dfisher_2022a/utils.py
dfisher_2022a-0.1.28.dist-info/LICENSE
dfisher_2022a-0.1.28.dist-info/WHEEL
dfisher_2022a-0.1.28.dist-info/METADATA
dfisher_2022a-0.1.28.dist-info/RECORD
