Metadata-Version: 2.1
Name: dfisher-2022a
Version: 0.1.28
Summary: Spectral analysis code created for the delivery of the DFisher_2022A ADACS MAP project.
Home-page: https://github.com/ADACS-Australia/dfisher_2022a
License: MIT-expat
Author: J. Hu
Author-email: jitinghu@swin.edu.au
Requires-Python: >=3.8,<3.10
Classifier: License :: Other/Proprietary License
Classifier: Programming Language :: Python :: 3
Classifier: Programming Language :: Python :: 3.8
Classifier: Programming Language :: Python :: 3.9
Provides-Extra: docs
Requires-Dist: Sphinx (==4.2.0); extra == "docs"
Requires-Dist: lmfit (>=1.0.3,<2.0.0)
Requires-Dist: mpdaf (>=3.5,<4.0)
Requires-Dist: numpy (>=1.19,<2.0)
Requires-Dist: pandas (>=1.4.2,<2.0.0)
Requires-Dist: sphinx-rtd-theme (==1.0.0); extra == "docs"
Requires-Dist: tables (>=3.7.0,<4.0.0)
Requires-Dist: tqdm (>=4.64.0,<5.0.0)
Project-URL: Documentation, https://dfisher-2022a.readthedocs.io/en/latest/
